cdi/ExcelSheetsConcat.py
cdi/__init__.py
cdi/exceldatahandler.py
ExcelSheetsConcat-0.2.0.dist-info/LICENCE
ExcelSheetsConcat-0.2.0.dist-info/METADATA
ExcelSheetsConcat-0.2.0.dist-info/WHEEL
ExcelSheetsConcat-0.2.0.dist-info/top_level.txt
ExcelSheetsConcat-0.2.0.dist-info/RECORD
