Metadata-Version: 2.1
Name: ExcelSheetsConcat
Version: 0.2.0
Summary: This package allow excel data handling
Home-page: https://github.com/simeanhamado/exceldatahandler
Author: Your Name
Author-email: geniestat.andal@gmail.com
Classifier: Programming Language :: Python :: 3
Classifier: License :: OSI Approved :: MIT License
Classifier: Operating System :: OS Independent
Requires-Python: >=3.6
License-File: LICENCE
Requires-Dist: numpy
Requires-Dist: pandas
Requires-Dist: openpyxl
